tgedr_pycommons/__init__.py
tgedr_pycommons/cicd/entrypoint.py
tgedr_pycommons/data/processing.py
tgedr_pycommons-0.0.7.dist-info/METADATA
tgedr_pycommons-0.0.7.dist-info/WHEEL
tgedr_pycommons-0.0.7.dist-info/top_level.txt
tgedr_pycommons-0.0.7.dist-info/RECORD
