Metadata-Version: 2.4
Name: tgedr-pycommons
Version: 0.0.7
Summary: common python code usable across projects
Author-email: joao tiago viegas <3536754+jtviegas@users.noreply.github.com>
Requires-Python: >=3.12
Requires-Dist: pandas>=2.3.0
